pwseqdist/__init__.py
pwseqdist/matrices.py
pwseqdist/metrics.py
pwseqdist/nb_metrics.py
pwseqdist/numba_tools.py
pwseqdist/pairwise.py
pwseqdist/running_metrics.py
pwseqdist/tests/__init__.py
pwseqdist/tests/test_distances.py
pwseqdist/tests/test_examples.py
pwseqdist/tests/test_matrices.py
pwseqdist/tests/test_numba_distances.py
pwseqdist-0.6.dist-info/LICENSE
pwseqdist-0.6.dist-info/METADATA
pwseqdist-0.6.dist-info/WHEEL
pwseqdist-0.6.dist-info/top_level.txt
pwseqdist-0.6.dist-info/RECORD
