Metadata-Version: 2.1
Name: pwseqdist
Version: 0.6
Summary: Efficiently computes distances between protein sequences
Home-page: https://github.com/agartland/pwseqdist
Author: Andrew Fiore-Gartland
Author-email: agartlan@fredhutch.org
Maintainer: Andrew Fiore-Gartland
Maintainer-email: agartlan@fredhutch.org
License: MIT
Platform: UNKNOWN
Requires-Dist: numpy (>=1.16.4)
Requires-Dist: pandas (>=0.24.2)
Requires-Dist: parasail (>=1.1.17)
Requires-Dist: parmap (>=1.5.2)
Requires-Dist: scipy (>=1.2.1)
Requires-Dist: numba
